jupyterlab_classiq/__init__.py
jupyterlab_classiq/_version.py
jupyterlab_classiq-0.105.0.data/data/share/jupyter/labextensions/jupyterlab-classiq/package.json
jupyterlab_classiq-0.105.0.data/data/share/jupyter/labextensions/jupyterlab-classiq/static/374.ab46446ed909b4554dba.js
jupyterlab_classiq-0.105.0.data/data/share/jupyter/labextensions/jupyterlab-classiq/static/374.ab46446ed909b4554dba.js.LICENSE.txt
jupyterlab_classiq-0.105.0.data/data/share/jupyter/labextensions/jupyterlab-classiq/static/codicon.raw.css
jupyterlab_classiq-0.105.0.data/data/share/jupyter/labextensions/jupyterlab-classiq/static/remoteEntry.1dadd691236ec2066df4.js
jupyterlab_classiq-0.105.0.data/data/share/jupyter/labextensions/jupyterlab-classiq/static/style.js
jupyterlab_classiq-0.105.0.data/data/share/jupyter/labextensions/jupyterlab-classiq/static/third-party-licenses.json
jupyterlab_classiq-0.105.0.data/data/share/jupyter/labextensions/jupyterlab-classiq/install.json
jupyterlab_classiq-0.105.0.dist-info/METADATA
jupyterlab_classiq-0.105.0.dist-info/WHEEL
jupyterlab_classiq-0.105.0.dist-info/RECORD
